utils/__init__.py
utils/test.py
rian_alba_tools-0.1.3.dist-info/LICENSE
rian_alba_tools-0.1.3.dist-info/METADATA
rian_alba_tools-0.1.3.dist-info/WHEEL
rian_alba_tools-0.1.3.dist-info/top_level.txt
rian_alba_tools-0.1.3.dist-info/RECORD
